{
  "source_name": "BulgarianProperties",
  "listing_url": "https://www.bulgarianproperties.com/2-bedroom_apartments_in_Bulgaria/AD89929BG_2-bedroom_apartment_for_rent_in_Sofia.html",
  "external_id": "8062d94bd739",
  "title": "Bulgarian Properties",
  "description": "Modern 2-bedroom apartment with brand new furniture and appliances next to Cherni Vrah Blvd.",
  "price": null,
  "currency": "EUR",
  "area_sqm": null,
  "rooms": null,
  "floor": null,
  "city": "",
  "district": "",
  "address_text": "",
  "latitude": null,
  "longitude": null,
  "listing_intent": "sale",
  "property_category": "apartment",
  "image_urls": [
    "https://static.bulgarianproperties.com/property-images/big/89929_10.jpg"
  ],
  "phones": [],
  "amenities": [],
  "scraped_at": "2026-04-08T16:36:48.612501+00:00",
  "reference_id": "BulgarianProperties:8062d94bd739",
  "local_image_files": [
    "data/media/BulgarianProperties_8062d94bd739/0000_7cd44c4b.jpg"
  ],
  "local_image_storage_keys": [
    "BulgarianProperties_8062d94bd739/0000_7cd44c4b.jpg"
  ]
}