{
  "source_name": "Address.bg",
  "listing_url": "https://address.bg/sofia-lyulin-3-dvustaen-apartament-offer681604",
  "external_id": "4dc4926282ae",
  "title": "Двустаен апартамент в София, Люлин 3 - код на имота: 681604",
  "description": "Адрес недвижими имоти предлага Двустаен апартамент в София, Люлин 3 с код на имота: 681604. Обадете се или изпратете запитване за информация и оглед на избраният от Вас недвижим имот.",
  "price": null,
  "currency": "EUR",
  "area_sqm": null,
  "rooms": null,
  "floor": null,
  "city": "",
  "district": "",
  "address_text": "",
  "latitude": null,
  "longitude": null,
  "listing_intent": "sale",
  "property_category": "apartment",
  "image_urls": [
    "https://address.bg/storage/uploads/offers/604/681604/764x510/1.jpg"
  ],
  "phones": [],
  "amenities": [],
  "scraped_at": "2026-04-09T11:21:18.877283+00:00",
  "reference_id": "Address.bg:4dc4926282ae",
  "local_image_files": [
    "data/media/Address.bg_4dc4926282ae/0000_3e3d018a.jpg"
  ],
  "local_image_storage_keys": [
    "Address.bg_4dc4926282ae/0000_3e3d018a.jpg"
  ]
}