{
  "source_name": "imot.bg",
  "listing_url": "https://www.imot.bg/obiava-1b177261786459012-prodava-dvustaen-apartament-grad-sofiya-levski-g",
  "external_id": "e42f7bff1005",
  "title": "Продава 2-СТАЕН град София, Левски Г Обява: 1b177261786459012",
  "description": "Предлага се за продажба стилен и съвременно завършен двустаен апартамент, съчетаващ функционалност, комфорт и модерна визия, с обща площ от 60 кв.м. Жилището е интелигентно разпределено и предлага уютна спалня, светла дневна зона с кухня и трапезария, широко входно антре с коридор и практично обособено мокро помещение, оборудвано с бойлер и пералня. Просторната тераса с достъп както от спалнята, така и от дневната създава усещане за допълнително пространство и връзка с външната среда. Интериорът е изпълнен с внимание към детайла и използване на висок клас материали, включително италиански гранитогрес и висококачествен швейцарски ламиниран паркет, които придават съвременен и изчистен облик на жилището. Банята е модерно завършена със санитарен фаянс и смесители ROCA, италиански гранитогрес и огледало с LED подсветка, съчетаващи стил и практичност. Кухнята е функционална, оборудвана с вградени електроуреди и модерен дизайн, създаващ комфортна среда за ежедневието. Източното изложение осигурява изобилие от естествена светлина и приятна атмосфера през целия ден. Сградата предлага високо ниво на сигурност и удобство чрез видеонаблюдение, контролиран достъп и асансьор Orona с чип система. Локацията е изключително комуникативна, в близост до автобусни спирки и само на пет минути пешеходно разстояние от метростанция на линия 3, което осигурява бърз достъп до всички ключови точки на града. Имотът е отличен избор както за лично ползване, така и за инвестиция с висок потенциал за доходност, благодарение на своята функционалност, качество на изпълнение и стратегическа локация.",
  "price": 190000.0,
  "currency": "EUR",
  "area_sqm": 60.0,
  "rooms": 2.0,
  "floor": 7.0,
  "city": "София",
  "district": "Левски Г",
  "address_text": "град София, Левски Г",
  "latitude": null,
  "longitude": null,
  "listing_intent": "sale",
  "property_category": "apartment",
  "image_urls": [
    "https://imotstatic2.focus.bg/imot/photosimotbg/1/012//big1/1b177261786459012_O0.jpg",
    "https://imotstatic2.focus.bg/imot/photosimotbg/1/012//big1/1b177261786459012_z7.jpg",
    "https://imotstatic2.focus.bg/imot/photosimotbg/1/012//big1/1b177261786459012_D2.jpg",
    "https://imotstatic2.focus.bg/imot/photosimotbg/1/012//big1/1b177261786459012_V8.jpg",
    "https://imotstatic2.focus.bg/imot/photosimotbg/1/012//big1/1b177261786459012_OX.jpg",
    "https://imotstatic2.focus.bg/imot/photosimotbg/1/012//big1/1b177261786459012_mK.jpg",
    "https://imotstatic2.focus.bg/imot/photosimotbg/1/012//big1/1b177261786459012_Pw.jpg",
    "https://imotstatic2.focus.bg/imot/photosimotbg/1/012//big1/1b177261786459012_YZ.jpg",
    "https://imotstatic2.focus.bg/imot/photosimotbg/1/012//big1/1b177261786459012_dI.jpg",
    "https://imotstatic2.focus.bg/imot/photosimotbg/1/012//big1/1b177261786459012_iz.jpg",
    "https://imotstatic2.focus.bg/imot/photosimotbg/1/012//big1/1b177261786459012_36.jpg",
    "https://imotstatic2.focus.bg/imot/photosimotbg/1/012//big1/1b177261786459012_AW.jpg",
    "https://imotstatic2.focus.bg/imot/photosimotbg/1/012//big1/1b177261786459012_n4.jpg",
    "https://imotstatic2.focus.bg/imot/photosimotbg/1/012//big1/1b177261786459012_AB.jpg",
    "https://imotstatic2.focus.bg/imot/photosimotbg/1/012//big1/1b177261786459012_rH.jpg",
    "https://imotstatic2.focus.bg/imot/photosimotbg/1/012//big1/1b177261786459012_l.jpg",
    "https://imotstatic2.focus.bg/imot/photosimotbg/1/012//big/1b177261786459012_O0.jpg"
  ],
  "phones": [
    "0884587131"
  ],
  "amenities": [
    "Площ: 60 m 2",
    "Етаж: 7-ми от 9",
    "Газ: НЕ",
    "Строителство: Тухла, Въведен в експлоатация 2022 г."
  ],
  "scraped_at": "2026-04-21T08:08:58.835821+00:00",
  "reference_id": "imot.bg:e42f7bff1005",
  "source_attributes": {
    "Площ": "60 m 2",
    "Етаж": "7-ми от 9",
    "Газ": "НЕ",
    "Строителство": "Тухла, Въведен в експлоатация 2022 г."
  },
  "listing_status": "active",
  "local_image_files": [
    "data/media/imot.bg_e42f7bff1005/0000_6c35fb32.jpg",
    "data/media/imot.bg_e42f7bff1005/0001_64b2cc01.jpg",
    "data/media/imot.bg_e42f7bff1005/0002_e84e83dd.jpg",
    "data/media/imot.bg_e42f7bff1005/0003_981cf594.jpg",
    "data/media/imot.bg_e42f7bff1005/0004_bae4aa5b.jpg",
    "data/media/imot.bg_e42f7bff1005/0005_b78776ae.jpg",
    "data/media/imot.bg_e42f7bff1005/0006_f7894ee3.jpg",
    "data/media/imot.bg_e42f7bff1005/0007_fae599be.jpg",
    "data/media/imot.bg_e42f7bff1005/0008_a4642b2d.jpg",
    "data/media/imot.bg_e42f7bff1005/0009_0964d921.jpg",
    "data/media/imot.bg_e42f7bff1005/0010_948ba0c3.jpg",
    "data/media/imot.bg_e42f7bff1005/0011_5d057361.jpg",
    "data/media/imot.bg_e42f7bff1005/0012_b9f174c2.jpg",
    "data/media/imot.bg_e42f7bff1005/0013_ce88d75f.jpg",
    "data/media/imot.bg_e42f7bff1005/0014_95b14f2e.jpg",
    "data/media/imot.bg_e42f7bff1005/0015_170f2a83.jpg",
    "data/media/imot.bg_e42f7bff1005/0016_975aa48b.jpg"
  ],
  "local_image_storage_keys": [
    "imot.bg_e42f7bff1005/0000_6c35fb32.jpg",
    "imot.bg_e42f7bff1005/0001_64b2cc01.jpg",
    "imot.bg_e42f7bff1005/0002_e84e83dd.jpg",
    "imot.bg_e42f7bff1005/0003_981cf594.jpg",
    "imot.bg_e42f7bff1005/0004_bae4aa5b.jpg",
    "imot.bg_e42f7bff1005/0005_b78776ae.jpg",
    "imot.bg_e42f7bff1005/0006_f7894ee3.jpg",
    "imot.bg_e42f7bff1005/0007_fae599be.jpg",
    "imot.bg_e42f7bff1005/0008_a4642b2d.jpg",
    "imot.bg_e42f7bff1005/0009_0964d921.jpg",
    "imot.bg_e42f7bff1005/0010_948ba0c3.jpg",
    "imot.bg_e42f7bff1005/0011_5d057361.jpg",
    "imot.bg_e42f7bff1005/0012_b9f174c2.jpg",
    "imot.bg_e42f7bff1005/0013_ce88d75f.jpg",
    "imot.bg_e42f7bff1005/0014_95b14f2e.jpg",
    "imot.bg_e42f7bff1005/0015_170f2a83.jpg",
    "imot.bg_e42f7bff1005/0016_975aa48b.jpg"
  ]
}