{
  "source_name": "imot.bg",
  "listing_url": "https://www.imot.bg/obiava-1a177314805991623-prodava-ednostaen-apartament-grad-sofiya-ovcha-kupel-2",
  "external_id": "6143be9dda03",
  "title": "魹ｽ魹ｽ魹ｽ魹ｽ魹ｽ魹ｽ魹ｽ 1-魹ｽ魹ｽ魹ｽ魹ｽ魹ｽ 魹ｽ魹ｽ魹ｽ魹ｽ 魹ｽ魹ｽ魹ｽ魹ｽ魹ｽ, 魹ｽ魹ｽ魹ｽ魹ｽ 魹ｽ魹ｽ魹ｽ魹ｽ魹ｽ 2 魹ｽ魹ｽ魹ｽ魹ｽ魹ｽ: 1a177314805991623",
  "description": "魹ｽ魹ｽ魹ｽ魹ｽ魹ｽ魹ｽ魹ｽ魹ｽ魹ｽ魹ｽ魹ｽ魹ｽ ! ! ! 魹ｽ魹ｽ魹ｽ ! ! ! 魹ｽ魹ｽ魹ｽ魹ｽ魹ｽ魹ｽ ! ! ! 魹ｽ魹ｽ魹ｽ魹ｽ 魹ｽ魹ｽ魹ｽ 16 ! ! ! 魹ｽ魹ｽ魹ｽ魹ｽ魹ｽ魹ｽ魹ｽ魹ｽ魹ｽ魹ｽ魹ｽ 魹ｽ魹ｽ 魹ｽ魹ｽ魹ｽ魹ｽ魹ｽ魹ｽ魹ｽ魹ｽ魹ｽ, 魹ｽ魹ｽ魹ｽ魹ｽ魹ｽ魹ｽ魹ｽ 魹ｽ魹ｽ 魹ｽ魹ｽ 5 魹ｽ魹ｽ魹ｽ. 魹ｽ魹ｽ 魹ｽ魹ｽ魹ｽ魹ｽ魹ｽ魹ｽ魹ｽ魹ｽ魹ｽ魹ｽ魹ｽ魹ｽ 魹ｽ魹ｽ魹ｽ魹ｽ魹ｽ. 魹ｽ魹ｽ魹ｽ魹ｽ魹ｽ魹ｽ魹ｽ魹ｽ 魹ｽ魹ｽ 魹ｽ魹ｽ魹ｽ魹ｽ魹ｽ魹ｽ 魹ｽ魹ｽ: 魹ｽ魹ｽ魹ｽ魹ｽ魹ｽ魹ｽ 魹ｽ魹ｽ魹ｽ魹ｽ魹ｽ, 魹ｽ魹ｽ魹ｽ魹ｽ 魹ｽ 魹ｽ魹ｽ魹ｽ魹ｽ魹ｽ魹ｽ魹ｽ魹ｽ, 魹ｽ魹ｽ魹ｽ魹ｽ魹ｽ魹ｽ 魹ｽ 魹ｽ魹ｽ魹ｽ魹ｽ魹ｽ魹ｽ魹ｽ魹ｽ魹ｽ 魹ｽ魹ｽ魹ｽ魹ｽ 魹ｽ 魹ｽ魹ｽ魹ｽ魹ｽ魹ｽ 魹ｽ魹ｽ 魹ｽ魹ｽ魹ｽ魹ｽ魹ｽ魹ｽ. 魹ｽ魹ｽ魹ｽ魹ｽ魹ｽ魹ｽ魹ｽ魹ｽ魹ｽ魹ｽ魹ｽ 魹ｽ 魹ｽ魹ｽ魹ｽ魹ｽ魹ｽ魹ｽ魹ｽ 魹ｽ魹ｽ魹ｽ魹ｽ魹ｽ魹ｽ魹ｽ魹ｽ魹ｽ, 魹ｽ魹ｽ魹ｽ魹ｽ魹ｽ魹ｽ魹ｽ魹ｽ魹ｽ 魹ｽ 5 魹ｽ魹ｽ魹ｽ魹ｽ魹ｽ魹ｽ魹ｽ 魹ｽ 魹ｽ魹ｽ魹ｽ魹ｽ魹ｽ 魹ｽ魹ｽ魹ｽ魹ｽ魹ｽ魹ｽ魹ｽ魹ｽ魹ｽ魹ｽ魹ｽ 魹ｽ魹ｽ魹ｽ魹ｽ魹ｽ魹ｽ 魹ｽ魹ｽ魹ｽ魹ｽ魹ｽ魹ｽ. 魹ｽ魹ｽ 魹ｽ魹ｽ魹ｽ魹ｽ 魹ｽ魹ｽ魹ｽ魹ｽ魹ｽ魹ｽ魹ｽ魹ｽ魹ｽ 魹ｽ魹ｽ魹ｽ魹ｽ魹ｽ魹ｽ魹ｽ魹ｽ魹ｽ 魹ｽ魹ｽ魹ｽ魹ｽ魹ｽ 魹ｽ魹ｽ 魹ｽ魹ｽ魹ｽ魹ｽ魹ｽ魹ｽ魹ｽ魹ｽ魹ｽ魹ｽ魹ｽ魹ｽ魹ｽ. 魹ｽ魹ｽ魹ｽ 魹ｽ魹ｽ魹ｽ魹ｽ魹ｽ魹ｽ魹ｽ 魹ｽ魹ｽ魹ｽ魹ｽ, 魹ｽ 魹ｽ魹ｽ魹ｽ魹ｽ 魹ｽ魹ｽ魹ｽ魹ｽ魹ｽ魹ｽ 魹ｽ魹ｽ 魹ｽ魹ｽ魹ｽ魹ｽ魹ｽ魹ｽ魹ｽ, 魹ｽ 魹ｽ魹ｽ魹ｽ魹ｽ魹ｽ魹ｽ魹ｽ魹ｽ魹ｽ魹ｽ 魹ｽ魹ｽ魹ｽ魹ｽ魹ｽ魹ｽ 魹ｽ魹ｽ 魹ｽ魹ｽ魹ｽ魹ｽ魹ｽ魹ｽ魹ｽ 魹ｽ 魹ｽ魹ｽ魹ｽ魹ｽ魹ｽ魹ｽ魹ｽ魹ｽ魹ｽ 魹ｽ魹ｽ魹ｽ魹ｽ魹ｽ魹ｽ魹ｽ 魹ｽ魹ｽ魹ｽ: 135606",
  "price": null,
  "currency": "EUR",
  "area_sqm": null,
  "rooms": null,
  "floor": null,
  "city": "魹ｽ魹ｽ魹ｽ魹ｽ 魹ｽ魹ｽ魹ｽ魹ｽ魹ｽ 2",
  "district": "魹ｽ魹ｽ魹ｽ魹ｽ 魹ｽ魹ｽ魹ｽ魹ｽ魹ｽ",
  "address_text": "魹ｽ魹ｽ魹ｽ魹ｽ 魹ｽ魹ｽ魹ｽ魹ｽ魹ｽ, 魹ｽ魹ｽ魹ｽ魹ｽ 魹ｽ魹ｽ魹ｽ魹ｽ魹ｽ 2",
  "latitude": null,
  "longitude": null,
  "listing_intent": "sale",
  "property_category": "apartment",
  "image_urls": [
    "https://imotstatic2.focus.bg/imot/photosimotbg/1/623//big1/1a177314805991623_7.jpg",
    "https://imotstatic2.focus.bg/imot/photosimotbg/1/623//big1/1a177314805991623_rG.jpg",
    "https://imotstatic2.focus.bg/imot/photosimotbg/1/623//big/1a177314805991623_bS.jpg",
    "https://imotstatic2.focus.bg/imot/photosimotbg/1/623//big1/1a177314805991623_Bw.jpg",
    "https://imotstatic2.focus.bg/imot/photosimotbg/1/623//big1/1a177314805991623_M3.jpg",
    "https://imotstatic2.focus.bg/imot/photosimotbg/1/623//big1/1a177314805991623_42.jpg",
    "https://imotstatic2.focus.bg/imot/photosimotbg/1/623//big1/1a177314805991623_D2.jpg",
    "https://imotstatic2.focus.bg/imot/photosimotbg/1/623//big1/1a177314805991623_6e.jpg",
    "https://imotstatic2.focus.bg/imot/photosimotbg/1/623//big/1a177314805991623_7.jpg"
  ],
  "phones": [
    "0875363330"
  ],
  "amenities": [
    "魹ｽ魹ｽ魹ｽ魹ｽ: 6-魹ｽ魹ｽ 魹ｽ魹ｽ 9",
    "魹ｽ魹ｽ魹ｽ魹ｽ魹ｽ魹ｽ魹ｽ魹ｽ魹ｽ魹ｽ魹ｽ魹ｽ: 魹ｽ魹ｽ魹ｽ魹ｽ魹ｽ, 魹ｽ魹ｽ 魹ｽ魹ｽ魹ｽ魹ｽ 魹ｽ魹ｽ魹ｽ魹ｽ魹ｽ魹ｽ魹ｽ 魹ｽ 魹ｽ魹ｽ魹ｽ魹ｽ魹ｽ魹ｽ魹ｽ魹ｽ魹ｽ魹ｽ魹ｽ魹ｽ 2026 魹ｽ."
  ],
  "scraped_at": "2026-04-24T07:52:33.216866+00:00",
  "reference_id": "imot.bg:6143be9dda03",
  "source_attributes": {
    "魹ｽ魹ｽ魹ｽ魹ｽ": "6-魹ｽ魹ｽ 魹ｽ魹ｽ 9",
    "魹ｽ魹ｽ魹ｽ魹ｽ魹ｽ魹ｽ魹ｽ魹ｽ魹ｽ魹ｽ魹ｽ魹ｽ": "魹ｽ魹ｽ魹ｽ魹ｽ魹ｽ, 魹ｽ魹ｽ 魹ｽ魹ｽ魹ｽ魹ｽ 魹ｽ魹ｽ魹ｽ魹ｽ魹ｽ魹ｽ魹ｽ 魹ｽ 魹ｽ魹ｽ魹ｽ魹ｽ魹ｽ魹ｽ魹ｽ魹ｽ魹ｽ魹ｽ魹ｽ魹ｽ 2026 魹ｽ."
  },
  "listing_status": "active",
  "local_image_files": [],
  "local_image_storage_keys": [],
  "local_media_dir": "data/media/imot.bg_6143be9dda03",
  "photo_count_remote": 9,
  "photo_count_local": 0,
  "full_gallery_downloaded": false,
  "photo_download_status": "no_local_files"
}