{
  "source_name": "imot.bg",
  "listing_url": "https://www.imot.bg/obiava-1a177518609149393-prodava-ednostaen-apartament-grad-sofiya-zona-b-19",
  "external_id": "6a91f0990ece",
  "title": "魹ｽ魹ｽ魹ｽ魹ｽ魹ｽ魹ｽ魹ｽ 1-魹ｽ魹ｽ魹ｽ魹ｽ魹ｽ 魹ｽ魹ｽ魹ｽ魹ｽ 魹ｽ魹ｽ魹ｽ魹ｽ魹ｽ, 魹ｽ魹ｽ魹ｽ魹ｽ 魹ｽ-19 魹ｽ魹ｽ魹ｽ魹ｽ魹ｽ: 1a177518609149393",
  "description": "魹ｽ魹ｽ魹ｽ魹ｽ魹ｽ魹ｽ   魹ｽ魹ｽ魹ｽ魹ｽ魹ｽ 魹ｽ魹ｽ魹ｽ魹ｽ魹ｽ魹ｽ魹ｽ 魹ｽ魹ｽ魹ｽ魹ｽ魹ｽ魹ｽ魹ｽ魹ｽ魹ｽ 魹ｽ魹ｽ魹ｽ魹ｽ魹ｽ魹ｽ魹ｽ魹ｽ魹ｽ魹ｽ 魹ｽ 魹ｽ魹ｽ魹ｽ魹ｽ魹ｽ魹ｽ魹ｽ 魹ｽ魹ｽ魹ｽ魹ｽ魹ｽ 魹ｽ 魹ｽ魹ｽ魹ｽ魹ｽ 魹ｽ-19 魹ｽ魹ｽ 魹ｽ魹ｽ. 魹ｽ魹ｽ魹ｽ魹ｽ魹ｽ魹ｽ  177 魹ｽ 魹ｽ魹ｽ魹ｽ魹ｽ   44 魹ｽ魹ｽ.魹ｽ. 魹ｽ魹ｽ魹ｽ魹ｽ魹ｽ魹ｽ魹ｽ 魹ｽ魹ｽ 魹ｽ魹ｽ: 魹ｽ魹ｽ魹ｽ魹ｽ魹ｽ魹ｽ 魹ｽ 魹ｽ魹ｽ魹ｽ 魹ｽ魹ｽ 魹ｽ魹ｽ魹ｽ魹ｽ魹ｽ, 魹ｽ魹ｽ魹ｽ魹ｽ魹ｽ, 魹ｽ魹ｽ魹ｽ魹ｽ魹ｽ魹ｽ, 魹ｽ魹ｽ魹ｽ魹ｽ魹ｽ 魹ｽ 魹ｽ魹ｽ魹ｽ魹ｽ 魹ｽ 魹ｽ魹ｽ魹ｽ魹ｽ魹ｽ魹ｽ魹ｽ魹ｽ. 魹ｽ魹ｽ魹ｽ魹ｽ魹ｽ魹ｽ魹ｽ魹ｽ魹ｽ魹ｽ魹ｽ 魹ｽ 魹ｽ魹ｽ魹ｽ魹ｽ魹ｽ魹ｽ魹ｽ 魹ｽ魹ｽ魹ｽ魹ｽ 魹ｽ魹ｽ 魹ｽ魹ｽ 魹ｽ魹ｽ魹ｽ. 魹ｽ魹ｽ魹ｽ魹ｽ魹ｽ魹ｽ 魹ｽ魹ｽ 魹ｽ魹ｽ魹ｽ魹ｽ魹ｽ魹ｽ 魹ｽ魹ｽ 魹ｽ魹ｽ魹ｽ魹ｽ魹ｽ 魹ｽ魹ｽ魹ｽ魹ｽ 魹ｽ 魹ｽ魹ｽ魹ｽ魹ｽ魹ｽ 魹ｽ魹ｽ魹ｽ 魹ｽ魹ｽ魹ｽ魹ｽ魹ｽ魹ｽ魹ｽ魹ｽ 魹ｽ魹ｽ魹ｽ魹ｽ, 魹ｽ魹ｽ魹ｽ魹ｽ魹ｽ魹ｽ 魹ｽ魹ｽ魹ｽ魹ｽ魹ｽ. 魹ｽ魹ｽ魹ｽ魹ｽ魹ｽ魹ｽ魹ｽ魹ｽ魹ｽ魹ｽ魹ｽ魹ｽ -  魹ｽ魹ｽ魹ｽ魹ｽ魹ｽ魹ｽ魹ｽ魹ｽ魹ｽ魹ｽ 魹ｽ魹ｽ魹ｽ魹ｽ魹ｽ魹ｽ魹ｽ魹ｽ  魹ｽ魹ｽ 魹ｽ魹ｽ魹ｽ魹ｽ魹ｽ魹ｽ 魹ｽ魹ｽ 魹ｽ魹ｽ魹ｽ魹ｽ魹ｽ魹ｽ 魹ｽ魹ｽ魹ｽ魹ｽ魹ｽ魹ｽ 魹ｽ魹ｽ魹ｽ魹ｽ魹ｽ魹ｽ魹ｽ魹ｽ魹ｽ 魹ｽ魹ｽ魹ｽ魹ｽ魹ｽ魹ｽ魹ｽ魹ｽ魹ｽ魹ｽ. 魹ｽ魹ｽ魹ｽ魹ｽ魹ｽ魹ｽ魹ｽ 魹ｽ 魹ｽ魹ｽ魹ｽ魹ｽ魹ｽ 魹ｽ 魹ｽ魹ｽ魹ｽ魹ｽ魹ｽ魹ｽ魹ｽ魹ｽ魹ｽ魹ｽ魹ｽ 魹ｽ魹ｽ魹ｽ魹ｽ魹ｽ魹ｽ魹ｽ魹ｽ 魹ｽ 魹ｽ魹ｽ魹ｽ魹ｽ魹ｽ 魹ｽ魹ｽ魹ｽ魹ｽ魹ｽ魹ｽ魹ｽ魹ｽ 魹ｽ魹ｽ 魹ｽ 魹ｽ 魹ｽ魹ｽ魹ｽ魹ｽ魹ｽ魹ｽ魹ｽ 魹ｽ魹ｽ魹ｽ 魹ｽ魹ｽ魹ｽ魹ｽ魹ｽ魹ｽ魹ｽ魹ｽ魹ｽ魹ｽ魹ｽ魹ｽ 魹ｽ魹ｽ 魹ｽ魹ｽ魹ｽ魹ｽ魹ｽ魹ｽ魹ｽ 魹ｽ魹ｽ魹ｽ魹ｽ 魹ｽ魹ｽ魹ｽ魹ｽ魹ｽ魹ｽ. 魹ｽ魹ｽ魹ｽ魹ｽ魹ｽ魹ｽ魹ｽ魹ｽ魹ｽ魹ｽ魹ｽ魹ｽ魹ｽ魹ｽ魹ｽ魹ｽ 魹ｽ 魹ｽ魹ｽ魹ｽ魹ｽ魹ｽ 魹ｽ魹ｽ魹ｽ魹ｽ魹ｽ 魹ｽ魹ｽ魹ｽ魹ｽ魹ｽ魹ｽ魹ｽ.  魹ｽ魹ｽ 魹ｽ魹ｽ魹ｽ魹ｽ魹ｽ 魹ｽ魹ｽ魹ｽ 魹ｽ魹ｽ魹ｽ魹ｽ魹ｽ 魹ｽ 魹ｽ魹ｽ魹ｽ魹ｽ 魹ｽ魹ｽ魹ｽ魹ｽ魹ｽ魹ｽ 魹ｽ 魹ｽ魹ｽ魹ｽ魹ｽ 魹ｽ魹ｽ 魹ｽ魹ｽ魹ｽ魹ｽ魹ｽ魹ｽ魹ｽ 魹ｽ魹ｽ 魹ｽ魹ｽ魹ｽ魹ｽ魹ｽ. 魹ｽ魹ｽ 魹ｽ魹ｽ魹ｽ魹ｽ魹ｽ魹ｽ 魹ｽ魹ｽ魹ｽ魹ｽ魹ｽ魹ｽ魹ｽ魹ｽ魹ｽ魹ｽ 魹ｽ 魹ｽ魹ｽ魹ｽ魹ｽ魹ｽ魹ｽ 魹ｽ魹ｽ魹ｽ魹ｽ魹ｽ魹ｽ魹ｽ魹ｽ魹ｽ 魹ｽ魹ｽ 魹ｽ魹ｽ魹ｽ魹ｽ魹ｽ魹ｽ魹ｽ魹ｽ魹ｽ 魹ｽ魹ｽ魹ｽ魹ｽ魹ｽ魹ｽ魹ｽ. 魹ｽ魹ｽ魹ｽ魹ｽ魹ｽ 魹ｽ魹ｽ魹ｽ魹ｽ魹ｽ魹ｽ - 魹ｽ魹ｽ魹ｽ魹ｽ魹ｽ魹ｽ 魹ｽ魹ｽ魹ｽ魹ｽ魹ｽ. (yavlenaCOM/168413).",
  "price": null,
  "currency": "EUR",
  "area_sqm": null,
  "rooms": null,
  "floor": null,
  "city": "魹ｽ魹ｽ魹ｽ魹ｽ 魹ｽ-19",
  "district": "魹ｽ魹ｽ魹ｽ魹ｽ 魹ｽ魹ｽ魹ｽ魹ｽ魹ｽ",
  "address_text": "魹ｽ魹ｽ魹ｽ魹ｽ 魹ｽ魹ｽ魹ｽ魹ｽ魹ｽ, 魹ｽ魹ｽ魹ｽ魹ｽ 魹ｽ-19",
  "latitude": null,
  "longitude": null,
  "listing_intent": "sale",
  "property_category": "apartment",
  "image_urls": [
    "https://imotstatic2.focus.bg/imot/photosimotbg/1/393//big/1a177518609149393_ml.jpg",
    "https://imotstatic2.focus.bg/imot/photosimotbg/1/393//big/1a177518609149393_3f.jpg",
    "https://imotstatic2.focus.bg/imot/photosimotbg/1/393//big/1a177518609149393_K7.jpg",
    "https://imotstatic2.focus.bg/imot/photosimotbg/1/393//big/1a177518609149393_Q3.jpg",
    "https://imotstatic2.focus.bg/imot/photosimotbg/1/393//big/1a177518609149393_Sx.jpg",
    "https://imotstatic2.focus.bg/imot/photosimotbg/1/393//big/1a177518609149393_ql.jpg",
    "https://imotstatic2.focus.bg/imot/photosimotbg/1/393//big/1a177518609149393_Yc.jpg",
    "https://imotstatic2.focus.bg/imot/photosimotbg/1/393//big/1a177518609149393_ml.jpg"
  ],
  "phones": [
    "0892515548",
    "222321",
    "4511827",
    "024511827"
  ],
  "amenities": [
    "魹ｽ魹ｽ魹ｽ魹ｽ: 2-魹ｽ魹ｽ 魹ｽ魹ｽ 7",
    "魹ｽ魹ｽ魹ｽ: 魹ｽ魹ｽ",
    "魹ｽE魹ｽ: 魹ｽ魹ｽ魹ｽ.魹ｽ魹ｽ魹ｽ魹ｽ魹ｽ.",
    "魹ｽ魹ｽ魹ｽ魹ｽ魹ｽ魹ｽ魹ｽ魹ｽ魹ｽ魹ｽ魹ｽ魹ｽ: 魹ｽ魹ｽ魹ｽ魹ｽ魹ｽ, 魹ｽ魹ｽ魹ｽ魹ｽ魹ｽ魹ｽ魹ｽ 魹ｽ 魹ｽ魹ｽ魹ｽ魹ｽ魹ｽ魹ｽ魹ｽ魹ｽ魹ｽ魹ｽ魹ｽ魹ｽ 2000 魹ｽ."
  ],
  "scraped_at": "2026-04-24T07:52:34.137678+00:00",
  "reference_id": "imot.bg:6a91f0990ece",
  "source_attributes": {
    "魹ｽ魹ｽ魹ｽ魹ｽ": "2-魹ｽ魹ｽ 魹ｽ魹ｽ 7",
    "魹ｽ魹ｽ魹ｽ": "魹ｽ魹ｽ",
    "魹ｽE魹ｽ": "魹ｽ魹ｽ魹ｽ.魹ｽ魹ｽ魹ｽ魹ｽ魹ｽ.",
    "魹ｽ魹ｽ魹ｽ魹ｽ魹ｽ魹ｽ魹ｽ魹ｽ魹ｽ魹ｽ魹ｽ魹ｽ": "魹ｽ魹ｽ魹ｽ魹ｽ魹ｽ, 魹ｽ魹ｽ魹ｽ魹ｽ魹ｽ魹ｽ魹ｽ 魹ｽ 魹ｽ魹ｽ魹ｽ魹ｽ魹ｽ魹ｽ魹ｽ魹ｽ魹ｽ魹ｽ魹ｽ魹ｽ 2000 魹ｽ."
  },
  "listing_status": "active",
  "contact_name": "魹ｽ魹ｽ魹ｽ魹ｽ魹ｽ魹ｽ  魹ｽ魹ｽ魹ｽ魹ｽ魹ｽ",
  "local_image_files": [],
  "local_image_storage_keys": [],
  "local_media_dir": "data/media/imot.bg_6a91f0990ece",
  "photo_count_remote": 8,
  "photo_count_local": 0,
  "full_gallery_downloaded": false,
  "photo_download_status": "no_local_files"
}