{
  "source_name": "Bazar.bg",
  "listing_url": "https://bazar.bg/obiava-54108077/dawa-pod-naem-1-staen-gr-sofiia-studentski-grad",
  "external_id": "54108077",
  "title": "Дава под наем 1-СТАЕН, гр. София, Студентски град → Обява 54108077",
  "description": "Дава под наем 1-СТАЕН, гр. София, Студентски град",
  "price": 486.0,
  "currency": "EUR",
  "area_sqm": 37.0,
  "rooms": 1.0,
  "floor": null,
  "city": "София",
  "district": "Студентски град",
  "address_text": "София, Студентски град",
  "latitude": null,
  "longitude": null,
  "listing_intent": "long_term_rent",
  "property_category": "unknown",
  "image_urls": [
    "https://imotstatic1.focus.bg/imot/photosimotbg/2/731/big/2b177126588845731_fQ.jpg",
    "https://imotstatic1.focus.bg/imot/photosimotbg/2/731/big/2b177126588845731_MF.jpg",
    "https://imotstatic1.focus.bg/imot/photosimotbg/2/731/big/2b177126588845731_Dz.jpg",
    "https://imotstatic1.focus.bg/imot/photosimotbg/2/731/big/2b177126588845731_Uz.jpg",
    "https://imotstatic1.focus.bg/imot/photosimotbg/2/731/big/2b177126588845731_Yc.jpg",
    "https://imotstatic1.focus.bg/imot/photosimotbg/2/731/big1/2b177126588845731_cZ.jpg",
    "https://imotstatic1.focus.bg/imot/photosimotbg/2/731/big1/2b177126588845731_5n.jpg",
    "https://imotstatic1.focus.bg/imot/photosimotbg/2/731/big1/2b177126588845731_t4.jpg",
    "https://imotstatic1.focus.bg/imot/photosimotbg/2/731/big/2b177126588845731_fQ.jpg"
  ],
  "phones": [
    "006135400",
    "0123456789",
    "01112551",
    "003-2014",
    "00000000",
    "089253959",
    "08974097",
    "07938466",
    "0026965905",
    "020087491",
    "0439541819",
    "08933920",
    "03123385",
    "08763328",
    "026-05-09",
    "000-2014"
  ],
  "amenities": [],
  "scraped_at": "2026-04-24T07:53:17.205959+00:00",
  "reference_id": "Bazar.bg:54108077",
  "local_image_files": [
    "data/media/Bazar.bg_54108077/0000_1134fac3.jpg",
    "data/media/Bazar.bg_54108077/0001_a52dd9dc.jpg",
    "data/media/Bazar.bg_54108077/0002_631b641f.jpg",
    "data/media/Bazar.bg_54108077/0003_1e88a753.jpg",
    "data/media/Bazar.bg_54108077/0004_9d2aad7c.jpg",
    "data/media/Bazar.bg_54108077/0005_fbc5bf9c.jpg",
    "data/media/Bazar.bg_54108077/0006_7cdd50ae.jpg",
    "data/media/Bazar.bg_54108077/0007_d8bcd4f0.jpg",
    "data/media/Bazar.bg_54108077/0008_1134fac3.jpg"
  ],
  "local_image_storage_keys": [
    "Bazar.bg_54108077/0000_1134fac3.jpg",
    "Bazar.bg_54108077/0001_a52dd9dc.jpg",
    "Bazar.bg_54108077/0002_631b641f.jpg",
    "Bazar.bg_54108077/0003_1e88a753.jpg",
    "Bazar.bg_54108077/0004_9d2aad7c.jpg",
    "Bazar.bg_54108077/0005_fbc5bf9c.jpg",
    "Bazar.bg_54108077/0006_7cdd50ae.jpg",
    "Bazar.bg_54108077/0007_d8bcd4f0.jpg",
    "Bazar.bg_54108077/0008_1134fac3.jpg"
  ],
  "local_media_dir": "data/media/Bazar.bg_54108077",
  "photo_count_remote": 9,
  "photo_count_local": 9,
  "full_gallery_downloaded": true,
  "photo_download_status": "full_gallery"
}