{
  "source_name": "Yavlena",
  "listing_url": "https://www.yavlena.com/bg/168363",
  "external_id": "1c541ff8204b",
  "title": "Двустаен апартамент в Несебър 92 кв.м. ID 168363  | Явлена",
  "description": "",
  "price": null,
  "currency": "EUR",
  "area_sqm": null,
  "rooms": null,
  "floor": null,
  "city": "",
  "district": "",
  "address_text": "",
  "latitude": null,
  "longitude": null,
  "listing_intent": "sale",
  "property_category": "apartment",
  "image_urls": [
    "https://userimages.yavlena.com/77ed361e-785a-4e0d-8f2a-3d7b972b30c1.JPG"
  ],
  "phones": [],
  "amenities": [],
  "scraped_at": "2026-04-08T17:13:36.689325+00:00",
  "reference_id": "Yavlena:1c541ff8204b",
  "local_image_files": [
    "data/media/Yavlena_1c541ff8204b/0000_759f2161.jpg"
  ],
  "local_image_storage_keys": [
    "Yavlena_1c541ff8204b/0000_759f2161.jpg"
  ]
}